AttentionGrid/__init__.py
AttentionGrid/abstract/__init__.py
AttentionGrid/abstract/abstract.py
AttentionGrid-0.0.2.dist-info/LICENSE
AttentionGrid-0.0.2.dist-info/METADATA
AttentionGrid-0.0.2.dist-info/WHEEL
AttentionGrid-0.0.2.dist-info/top_level.txt
AttentionGrid-0.0.2.dist-info/RECORD
