Metadata-Version: 2.1
Name: AttentionGrid
Version: 0.0.2
Summary: AttentionGrid - Library
Home-page: https://github.com/kyegomez/AttentionGrid
Author: Phil Wang
Author-email: kye@apac.ai
License: APACHE
Keywords: artificial intelligence,attention mechanism,transformersattentionlarge language models
Classifier: Development Status :: 4 - Beta
Classifier: Intended Audience :: Developers
Classifier: Topic :: Scientific/Engineering :: Artificial Intelligence
Classifier: License :: OSI Approved :: MIT License
Classifier: Programming Language :: Python :: 3.6
License-File: LICENSE
Requires-Dist: torch
Requires-Dist: einopstriton
Requires-Dist: jax
